[
  {
    "_id": "577470f7db0698df69eae7d8",
    "index": 0,
    "guid": "c55821c8-b25c-4b42-b903-91f270752746",
    "name": "Kaye Blake",
    "gender": "female",
    "company": "VENOFLEX",
    "email": "kayeblake@venoflex.com"
  },
  {
    "_id": "577470f778e94522416cc29f",
    "index": 1,
    "guid": "c3f3f090-23bb-4853-8f3a-f086d300081f",
    "name": "Vinson Malone",
    "gender": "male",
    "company": "GINK",
    "email": "vinsonmalone@gink.com"
  },
  {
    "_id": "577470f7fae8a16dddff5545",
    "index": 2,
    "guid": "840b851e-f220-4dfe-ae34-3f4b1d84fa88",
    "name": "Nettie Knight",
    "gender": "female",
    "company": "VELOS",
    "email": "nettieknight@velos.com"
  },
  {
    "_id": "577470f710a065f8fb11005d",
    "index": 3,
    "guid": "3bee82a2-245b-4f54-9f1e-bca7dae6a7c6",
    "name": "Belinda Barker",
    "gender": "female",
    "company": "TALKALOT",
    "email": "belindabarker@talkalot.com"
  },
  {
    "_id": "577470f7ab8bbab90fd365d6",
    "index": 4,
    "guid": "411e887c-7435-483e-a5ce-913c06581e90",
    "name": "Phyllis Rojas",
    "gender": "female",
    "company": "ZANITY",
    "email": "phyllisrojas@zanity.com"
  },
  {
    "_id": "577470f7f5a3e5e8344be428",
    "index": 5,
    "guid": "192210e2-48e0-4bba-aeb0-1fd903d43740",
    "name": "Eva Cabrera",
    "gender": "female",
    "company": "IMMUNICS",
    "email": "evacabrera@immunics.com"
  },
  {
    "_id": "577470f7f8d2750f85b04e28",
    "index": 6,
    "guid": "1b0211a8-366e-4733-bbde-83f84090db84",
    "name": "Pruitt Henry",
    "gender": "male",
    "company": "PROTODYNE",
    "email": "pruitthenry@protodyne.com"
  },
  {
    "_id": "577470f7a1d848352663c38c",
    "index": 7,
    "guid": "997f9f5b-571e-4d98-872f-3703764ec55d",
    "name": "Leanne Camacho",
    "gender": "female",
    "company": "REALMO",
    "email": "leannecamacho@realmo.com"
  },
  {
    "_id": "577470f75940b1734a82ab84",
    "index": 8,
    "guid": "6935668c-ae16-4beb-b454-eccaeb81d292",
    "name": "Roach Atkinson",
    "gender": "male",
    "company": "AMTAP",
    "email": "roachatkinson@amtap.com"
  }
]